{"data":{"location":{"name":"Buena Park YARD west end","id":"-d2256334-5641-5d69-b26b-1726c5127c7d","radioChannel":"32","additionalInfo":"You need to drive through the warehouse parking lot and around the back of the building","googleMapsUrl":"https://goo.gl/maps/WBKw83ruBFL2","appleMapsUrl":"https://maps.apple.com/?address=15073%E2%80%9315137%20Northam%20St,%20La%20Mirada,%20CA%20%2090638,%20United%20States&ll=33.884417,-118.010306&q=15073%E2%80%9315137%20Northam%20St&_ext=EiYpUsME1Z/wQEAxROe97gKBXcA50JgqMcbxQEBB4mJ2pFGAXcBQBA%3D%3D&t=m","image":null}},"pageContext":{"slug":"buena-park-yard-west-end"}}